span_extructure/__init__.py
span_extructure/main.py
span_extructure-0.1.1.dist-info/entry_points.txt
span_extructure-0.1.1.dist-info/LICENSE
span_extructure-0.1.1.dist-info/WHEEL
span_extructure-0.1.1.dist-info/METADATA
span_extructure-0.1.1.dist-info/RECORD
